PyFakeDados/CONSTANTS.py
PyFakeDados/__init__.py
PyFakeDados/bairro.py
PyFakeDados/cep.py
PyFakeDados/cnpj.py
PyFakeDados/cpf.py
PyFakeDados/ctps.py
PyFakeDados/email.py
PyFakeDados/empresa.py
PyFakeDados/endereco.py
PyFakeDados/estado.py
PyFakeDados/inscricao_estadual.py
PyFakeDados/logradouro.py
PyFakeDados/municipio.py
PyFakeDados/nome.py
PyFakeDados/pessoa.py
PyFakeDados/pis.py
PyFakeDados/rg.py
PyFakeDados/senha.py
PyFakeDados/site.py
PyFakeDados/telefone.py
PyFakeDados/utils.py
PyFakeDados-0.0.5.3.dist-info/LICENSE.txt
PyFakeDados-0.0.5.3.dist-info/METADATA
PyFakeDados-0.0.5.3.dist-info/WHEEL
PyFakeDados-0.0.5.3.dist-info/top_level.txt
PyFakeDados-0.0.5.3.dist-info/RECORD
